python_to_typescript_interfaces/__init__.py
python_to_typescript_interfaces/cli.py
python_to_typescript_interfaces/parser.py
python_to_typescript_interfaces/py.typed
python_to_typescript_interfaces/tests/__init__.py
python_to_typescript_interfaces/tests/tests.py
python_to_typescript_interfaces/tests/utils.py
python_to_typescript_interfaces-0.2.0.dist-info/LICENSE
python_to_typescript_interfaces-0.2.0.dist-info/METADATA
python_to_typescript_interfaces-0.2.0.dist-info/WHEEL
python_to_typescript_interfaces-0.2.0.dist-info/entry_points.txt
python_to_typescript_interfaces-0.2.0.dist-info/RECORD
