Metadata-Version: 2.1
Name: python-to-typescript-interfaces
Version: 0.2.0
Summary: A library that converts Python dataclasses with type annotations to a TypeScript interface and serializes them to a file. Originally py-ts-interfaces
Home-page: https://github.com/NalyzeSolutions/python_to_typescript_interfaces
License: MIT
Keywords: python,typescript,interfaces
Author: Christopher Cordero
Author-email: ccordero@protonmail.com
Requires-Python: >=3.8.1,<4.0.0
Classifier: License :: OSI Approved :: MIT License
Classifier: Operating System :: OS Independent
Classifier: Programming Language :: Python
Classifier: Programming Language :: Python :: 3
Classifier: Programming Language :: Python :: 3.9
Classifier: Programming Language :: Python :: 3.10
Classifier: Programming Language :: Python :: 3.11
Classifier: Programming Language :: Python :: 3.12
Classifier: Programming Language :: Python :: 3 :: Only
Classifier: Programming Language :: Python :: 3.8
Classifier: Typing :: Typed
Requires-Dist: astroid (==3.2.1)
Project-URL: Documentation, https://github.com/NalyzeSolutions/python_to_typescript_interfaces
Project-URL: Repository, https://github.com/NalyzeSolutions/python_to_typescript_interfaces
